{
  "id": "lin-07",
  "title": "The Elimination Engine",
  "kingdom": "linear-equations",
  "dungeonNumber": 7,
  "lesson": {
    "title": "Systems by Elimination",
    "body": "The **elimination method** adds or subtracts the two equations to cancel out one variable. If one variable has opposite coefficients, add the equations directly. If not, multiply one (or both) equations by a constant first to create matching coefficients. Example: 2x + 3y = 12 and 2x − y = 4. Subtract the second from the first: 4y = 8 → y = 2. Back-substitute: 2x + 6 = 12 → x = 3."
  },
  "rooms": [
    {
      "type": "multiple-choice",
      "question": "Use elimination to solve: x + y = 8 and x − y = 2",
      "latex": "x + y = 8 \\quad x - y = 2",
      "steps": [
        "\\text{Add equations: } 2x = 10 \\Rightarrow x = 5",
        "\\text{Back-sub: } 5 + y = 8 \\Rightarrow y = 3"
      ],
      "answers": [
        "(3, 5)",
        "(5, 3)",
        "(4, 4)",
        "(6, 2)"
      ],
      "correct": 1,
      "difficulty": 1,
      "explanation": "Add the equations: (x+y) + (x−y) = 8+2 → 2x = 10 → x = 5. Then y = 8 − 5 = 3. Solution: (5, 3). Check: 5+3=8 ✓ and 5−3=2 ✓. The y terms canceled because they are opposites (+y and −y).",
      "xp": 10
    },
    {
      "type": "multiple-choice",
      "question": "Use elimination: 3x + 2y = 10 and 3x − y = 4",
      "latex": "3x + 2y = 10 \\quad 3x - y = 4",
      "steps": [
        "\\text{Subtract: } (3x + 2y) - (3x - y) = 10 - 4",
        "3y = 6 \\Rightarrow y = 2",
        "3x + 4 = 10 \\Rightarrow x = 2"
      ],
      "answers": [
        "(1, 2)",
        "(2, 2)",
        "(3, 1)",
        "(2, 3)"
      ],
      "correct": 1,
      "difficulty": 1,
      "explanation": "Subtract equation 2 from equation 1 to eliminate x: 3y = 6 → y = 2. Back-sub: 3x + 2(2) = 10 → 3x = 6 → x = 2. Solution: (2, 2). Check: 3(2)+2(2)=10 ✓ and 3(2)−2=4 ✓.",
      "xp": 10
    },
    {
      "type": "multiple-choice",
      "question": "To eliminate x from: 2x + 5y = 14 and 3x − y = 3, you multiply the first equation by 3 and the second by 2. What is the new system?",
      "latex": "2x + 5y = 14 \\quad 3x - y = 3",
      "steps": [
        "\\text{Multiply eq1 by 3: } 6x + 15y = 42",
        "\\text{Multiply eq2 by 2: } 6x - 2y = 6"
      ],
      "answers": [
        "6x + 15y = 42 and 6x − 2y = 6",
        "5x + 15y = 42 and 5x − y = 3",
        "6x + 8y = 42 and 6x − 2y = 6",
        "6x + 5y = 14 and 6x − y = 3"
      ],
      "correct": 0,
      "difficulty": 2,
      "explanation": "Multiply every term in equation 1 by 3: 6x + 15y = 42. Multiply every term in equation 2 by 2: 6x − 2y = 6. Now both have 6x — subtracting will eliminate x. Multiplying must apply to all terms including the constant.",
      "xp": 10
    },
    {
      "type": "multiple-choice",
      "question": "Solve by elimination: x + 2y = 7 and 2x − y = 4",
      "latex": "x + 2y = 7 \\quad 2x - y = 4",
      "steps": [
        "\\text{Multiply eq2 by 2: } 4x - 2y = 8",
        "\\text{Add: } 5x = 15 \\Rightarrow x = 3",
        "3 + 2y = 7 \\Rightarrow y = 2"
      ],
      "answers": [
        "(1, 3)",
        "(2, 3)",
        "(3, 2)",
        "(4, 1)"
      ],
      "correct": 2,
      "difficulty": 2,
      "explanation": "Multiply equation 2 by 2 to get +4x − 2y = 8. Add to equation 1: x + 2y + 4x − 2y = 7 + 8 → 5x = 15 → x = 3. Then 3 + 2y = 7 → y = 2. Check: 3+4=7 ✓ and 6−2=4 ✓.",
      "xp": 10
    },
    {
      "type": "drag-and-drop",
      "question": "Put the elimination steps in order for: 3x + 4y = 11 and 5x − 2y = 1",
      "items": [
        "Multiply eq2 by 2: 10x − 4y = 2",
        "Add equations: 13x = 13 → x = 1",
        "Back-substitute: 3(1) + 4y = 11 → y = 2",
        "Check: 3+8=11 ✓ and 5−4=1 ✓"
      ],
      "correctOrder": [
        0,
        1,
        2,
        3
      ],
      "difficulty": 3,
      "explanation": "Multiply eq2 by 2 to get 4y with opposite sign → add to eliminate y → solve for x → back-substitute → verify. The solution (1, 2) can also be verified: 5(1)−2(2) = 5−4 = 1 ✓.",
      "xp": 20
    }
  ],
  "boss": {
    "name": "The Eliminator",
    "taunt": "I eliminate variables. And students.",
    "questions": [
      {
        "type": "multiple-choice",
        "question": "Solve by elimination: 4x + 3y = 18 and 2x − 3y = 0",
        "latex": "4x + 3y = 18 \\quad 2x - 3y = 0",
        "answers": [
          "(2, 2)",
          "(3, 2)",
          "(2, 3)",
          "(3, 3)"
        ],
        "correct": 1,
        "difficulty": 2,
        "explanation": "Add equations (the 3y terms cancel): 6x = 18 → x = 3. Back-sub into eq2: 2(3) − 3y = 0 → 3y = 6 → y = 2. Solution: (3, 2). Check: 4(3)+3(2)=18 ✓ and 2(3)−3(2)=0 ✓.",
        "xp": 25
      },
      {
        "type": "multiple-choice",
        "question": "The sum of two numbers is 40. Three times the first minus the second equals 20. What is the first number?",
        "latex": "x + y = 40 \\quad 3x - y = 20",
        "answers": [
          "12",
          "15",
          "20",
          "25"
        ],
        "correct": 1,
        "difficulty": 2,
        "explanation": "Add both equations to eliminate y: (x+y)+(3x−y) = 40+20 → 4x = 60 → x = 15. Then y = 40 − 15 = 25. Check: 3(15)−25 = 45−25 = 20 ✓. The first number is 15.",
        "xp": 25
      },
      {
        "type": "multiple-choice",
        "question": "Solve: 2x + 3y = 16 and 3x + 2y = 14",
        "latex": "2x + 3y = 16 \\quad 3x + 2y = 14",
        "answers": [
          "(2, 4)",
          "(4, 2)",
          "(1, 5)",
          "(3, 3)"
        ],
        "correct": 0,
        "difficulty": 3,
        "explanation": "Multiply eq1 by 3 and eq2 by 2: 6x+9y=48 and 6x+4y=28. Subtract: 5y = 20 → y = 4. Back-sub: 2x+12=16 → x = 2. Solution: (2, 4). Check: 2(2)+3(4)=4+12=16 ✓ and 3(2)+2(4)=6+8=14 ✓.",
        "xp": 25
      }
    ],
    "passMark": 2,
    "lootTable": [
      {
        "type": "hint-scroll",
        "weight": 25
      },
      {
        "type": "focus-crystal",
        "weight": 35
      },
      {
        "type": "scholars-tome",
        "weight": 28
      },
      {
        "type": "solution-orb",
        "weight": 12
      }
    ]
  },
  "lootTable": []
}
