{
  "id": "quad-03",
  "title": "The Square Root Sanctum",
  "kingdom": "quadratics",
  "dungeonNumber": 3,
  "lesson": {
    "title": "Solving Quadratics by Square Roots",
    "body": "When a quadratic has no middle term (b = 0), use the **square root method**: (1) Isolate x¬≤. (2) Take ¬Ī‚ąö of both sides. Remember ¬Ī ‚ÄĒ there are two roots. Example: 3x¬≤ ‚ąí 48 = 0 ‚Üí 3x¬≤ = 48 ‚Üí x¬≤ = 16 ‚Üí x = ¬Ī4. This also works when the squared expression is a binomial: (x ‚ąí 3)¬≤ = 25 ‚Üí x ‚ąí 3 = ¬Ī5 ‚Üí x = 8 or x = ‚ąí2. Works best when the equation is already in the form (ax + b)¬≤ = c."
  },
  "rooms": [
    {
      "type": "multiple-choice",
      "question": "Solve: x¬≤ = 49",
      "latex": "x^2 = 49",
      "steps": [
        "x = \\pm\\sqrt{49} = \\pm 7"
      ],
      "answers": [
        "x = 7",
        "x = ¬Ī7",
        "x = ¬Ī49",
        "x = ‚ąö49"
      ],
      "correct": 1,
      "difficulty": 1,
      "explanation": "x¬≤=49 ‚Üí x=¬Ī‚ąö49=¬Ī7. Both 7 and ‚ąí7 are solutions because 7¬≤=49 and (‚ąí7)¬≤=49. Forgetting the ¬Ī is the most common error ‚ÄĒ x=7 alone is incomplete.",
      "xp": 10
    },
    {
      "type": "multiple-choice",
      "question": "Solve: 2x¬≤ ‚ąí 50 = 0",
      "latex": "2x^2 - 50 = 0",
      "steps": [
        "2x^2 = 50 \\Rightarrow x^2 = 25",
        "x = \\pm 5"
      ],
      "answers": [
        "x = ¬Ī‚ąö25",
        "x = ¬Ī5",
        "x = 5",
        "x = ¬Ī‚ąö50"
      ],
      "correct": 1,
      "difficulty": 1,
      "explanation": "Isolate x¬≤: 2x¬≤=50 ‚Üí x¬≤=25 ‚Üí x=¬Ī5. Note: ¬Ī‚ąö25 = ¬Ī5 (same answer) ‚ÄĒ option A is technically equivalent but not simplified. Standard form is ¬Ī5.",
      "xp": 10
    },
    {
      "type": "multiple-choice",
      "question": "Solve: (x + 3)¬≤ = 16",
      "latex": "(x + 3)^2 = 16",
      "steps": [
        "x + 3 = \\pm 4",
        "x = 1 \\text{ or } x = -7"
      ],
      "answers": [
        "x = 1 or x = ‚ąí1",
        "x = 7 or x = ‚ąí7",
        "x = 1 or x = ‚ąí7",
        "x = 13 or x = ‚ąí13"
      ],
      "correct": 2,
      "difficulty": 2,
      "explanation": "Take ¬Ī‚ąö: x+3=¬Ī4. Case 1: x+3=4 ‚Üí x=1. Case 2: x+3=‚ąí4 ‚Üí x=‚ąí7. Two solutions: x=1 or x=‚ąí7. Check: (1+3)¬≤=16 ‚úď and (‚ąí7+3)¬≤=(‚ąí4)¬≤=16 ‚úď.",
      "xp": 10
    },
    {
      "type": "multiple-choice",
      "question": "Solve: 3(x ‚ąí 1)¬≤ = 75",
      "latex": "3(x-1)^2 = 75",
      "steps": [
        "(x - 1)^2 = 25",
        "x - 1 = \\pm 5",
        "x = 6 \\text{ or } x = -4"
      ],
      "answers": [
        "x = 4 or x = ‚ąí6",
        "x = 6 or x = ‚ąí4",
        "x = ¬Ī5",
        "x = 26 or x = ‚ąí24"
      ],
      "correct": 1,
      "difficulty": 2,
      "explanation": "Divide by 3: (x‚ąí1)¬≤=25. Take ¬Ī‚ąö: x‚ąí1=¬Ī5. Case 1: x‚ąí1=5 ‚Üí x=6. Case 2: x‚ąí1=‚ąí5 ‚Üí x=‚ąí4. Check: 3(5)¬≤=75 ‚úď and 3(‚ąí5)¬≤=75 ‚úď.",
      "xp": 10
    },
    {
      "type": "drag-and-drop",
      "question": "Order the steps to solve: 4(x + 2)¬≤ ‚ąí 36 = 0",
      "items": [
        "Add 36: 4(x + 2)¬≤ = 36",
        "Divide by 4: (x + 2)¬≤ = 9",
        "Take square roots: x + 2 = ¬Ī3",
        "Solve: x = 1 or x = ‚ąí5"
      ],
      "correctOrder": [
        0,
        1,
        2,
        3
      ],
      "difficulty": 3,
      "explanation": "Isolate the squared expression ‚Üí divide ‚Üí take ¬Ī‚ąö ‚Üí solve the two linear equations. Check: 4(3)¬≤‚ąí36=36‚ąí36=0 ‚úď and 4(‚ąí3)¬≤‚ąí36=36‚ąí36=0 ‚úď.",
      "xp": 20
    }
  ],
  "boss": {
    "name": "The Square Root Wraith",
    "taunt": "¬Ī. Both answers lead to me.",
    "questions": [
      {
        "type": "multiple-choice",
        "question": "Solve: 5x¬≤ + 20 = 0",
        "latex": "5x^2 + 20 = 0",
        "answers": [
          "x = ¬Ī2",
          "x = ¬Ī2i",
          "No real solution",
          "x = ¬Ī4"
        ],
        "correct": 2,
        "difficulty": 2,
        "explanation": "5x¬≤=‚ąí20 ‚Üí x¬≤=‚ąí4. A square cannot be negative in the real numbers, so there is no real solution. The solutions are x=¬Ī2i (complex), but those are outside this course's scope.",
        "xp": 25
      },
      {
        "type": "multiple-choice",
        "question": "Solve: (2x ‚ąí 1)¬≤ = 9",
        "latex": "(2x - 1)^2 = 9",
        "answers": [
          "x = 2 or x = ‚ąí1",
          "x = 1 or x = ‚ąí2",
          "x = 5 or x = ‚ąí4",
          "x = 4 or x = ‚ąí2"
        ],
        "correct": 0,
        "difficulty": 2,
        "explanation": "Take ¬Ī‚ąö: 2x‚ąí1=¬Ī3. Case 1: 2x‚ąí1=3 ‚Üí 2x=4 ‚Üí x=2. Case 2: 2x‚ąí1=‚ąí3 ‚Üí 2x=‚ąí2 ‚Üí x=‚ąí1. Solutions: x=2 or x=‚ąí1. Check: (4‚ąí1)¬≤=9 ‚úď and (‚ąí2‚ąí1)¬≤=9 ‚úď.",
        "xp": 25
      },
      {
        "type": "multiple-choice",
        "question": "A ball dropped from height h falls s = 5t¬≤ meters in t seconds. From a cliff 80 m high, when does it land?",
        "latex": "5t^2 = 80",
        "answers": [
          "t = 2 s",
          "t = 4 s",
          "t = 8 s",
          "t = ¬Ī4 s"
        ],
        "correct": 1,
        "difficulty": 3,
        "explanation": "5t¬≤=80 ‚Üí t¬≤=16 ‚Üí t=¬Ī4. Since time is positive, t=4 seconds. The ¬Ī4 answer is mathematically correct but context eliminates the negative: we can't have t=‚ąí4. Always check physical meaning when solving real-world problems.",
        "xp": 25
      }
    ],
    "passMark": 2,
    "lootTable": [
      {
        "type": "hint-scroll",
        "weight": 70
      },
      {
        "type": "focus-crystal",
        "weight": 20
      },
      {
        "type": "scholars-tome",
        "weight": 7
      },
      {
        "type": "solution-orb",
        "weight": 3
      }
    ]
  },
  "lootTable": []
}
